{"stats":{"minecraft:used":{"outta_pocket:relay":2,"minecraft:grass_block":9,"minecraft:stonecutter":3,"minecraft:piston":1,"outta_pocket:gear":4,"outta_pocket:cyan_rose":1,"outta_pocket:red_rose":1,"minecraft:stone_pickaxe":8,"outta_pocket:stonecutter":2},"minecraft:mined":{"outta_pocket:stonecutter":3,"outta_pocket:motor":1,"minecraft:piston":1,"minecraft:stonecutter":2,"outta_pocket:relay":2},"minecraft:custom":{"minecraft:time_since_rest":1956,"minecraft:walk_one_cm":4999,"minecraft:total_world_time":1976,"minecraft:leave_game":1,"minecraft:play_time":1956,"minecraft:interact_with_stonecutter":2,"minecraft:jump":3,"minecraft:time_since_death":1956},"minecraft:picked_up":{"outta_pocket:relay":2,"minecraft:stonecutter":2,"outta_pocket:motor":1,"minecraft:piston":1,"outta_pocket:stonecutter":3}},"DataVersion":4556}